problemator/__init__.py
problemator/problemator.py
problemator-1.2.0.dist-info/LICENSE
problemator-1.2.0.dist-info/METADATA
problemator-1.2.0.dist-info/WHEEL
problemator-1.2.0.dist-info/top_level.txt
problemator-1.2.0.dist-info/RECORD
