Metadata-Version: 2.1
Name: problemator
Version: 1.2.0
Summary: WolframAlpha's Unlimited AI-generated practice problems and answers API wrapper.
Home-page: https://github.com/DedInc/problemator
Author: Maehdakvan
Author-email: visitanimation@google.com
Project-URL: Bug Tracker, https://github.com/DedInc/problemator/issues
Classifier: Programming Language :: Python :: 3
Classifier: License :: OSI Approved :: MIT License
Classifier: Operating System :: OS Independent
Requires-Python: >=3.0
License-File: LICENSE
Requires-Dist: requests
Requires-Dist: user-agent
